llm_scheduler/__init__.py
llm_scheduler/utils.py
llm_scheduler/core/config.py
llm_scheduler/core/health.py
llm_scheduler/core/job_scheduler.py
llm_scheduler/core/llm_executor.py
llm_scheduler/core/logger.py
llm_scheduler/core/metrics.py
llm_scheduler/core/scheduler.py
llm_scheduler/core/storage.py
llm_scheduler/core/time_utils.py
llm_scheduler/core/tool_registry.py
llm_scheduler/core/types.py
llm_scheduler/examples/advanced_usage.py
llm_scheduler/examples/api_usage.py
llm_scheduler/examples/basic_usage.py
llm_scheduler/examples/complex_tools.py
llm_scheduler/tools/__init__.py
llm_scheduler/tools/base.py
llm_scheduler/tools/base/__init__.py
llm_scheduler/tools/base/tool.py
llm_scheduler/tools/builtin/__init__.py
llm_scheduler/tools/builtin/calendar.py
llm_scheduler/tools/builtin/sms.py
llm_scheduler/tools/builtin/weather.py
llm_scheduler-0.2.2.dist-info/LICENSE
llm_scheduler-0.2.2.dist-info/METADATA
llm_scheduler-0.2.2.dist-info/WHEEL
llm_scheduler-0.2.2.dist-info/top_level.txt
llm_scheduler-0.2.2.dist-info/RECORD
